CHANGES.txt
MANIFEST.in
README.rst
buildout.cfg
development.ini
production.ini
setup.py
liches/__init__.py
liches/models.py
liches/tests.py
liches/utils.py
liches/views.py
liches.egg-info/PKG-INFO
liches.egg-info/SOURCES.txt
liches.egg-info/dependency_links.txt
liches.egg-info/entry_points.txt
liches.egg-info/not-zip-safe
liches.egg-info/requires.txt
liches.egg-info/top_level.txt
liches/scripts/__init__.py
liches/scripts/checklinks.py
liches/scripts/checkpage.py
liches/scripts/checkpage.sh
liches/scripts/emptydb.py
liches/scripts/importcsv.py
liches/scripts/initializedb.py
liches/static/favicon.ico
liches/static/footerbg.png
liches/static/headerbg.png
liches/static/ie6.css
liches/static/middlebg.png
liches/static/pylons.css
liches/static/pyramid-small.png
liches/static/pyramid.png
liches/static/transparent.gif
liches/templates/checklink.pt
liches/templates/home.pt
liches/templates/linkcheck_add.pt
liches/templates/linkcheck_edit.pt
liches/templates/linkchecks.pt
liches/templates/pages.pt
liches/templates/parenturl.pt
liches/templates/user_add.pt
liches/templates/user_edit.pt