Metadata-Version: 1.1
Name: liches
Version: 0.7
Summary: Liches a server for linkchecker results
Home-page: https://github.com/cleder/liches
Author: Christian Ledermann
Author-email: christian.ledermann@gmail.com
License: GPL
Keywords: web wsgi bfg pylons pyramid linkchecker
Platform: UNKNOWN
Classifier: Programming Language :: Python
Classifier: Framework :: Pyramid
Classifier: Topic :: Internet :: WWW/HTTP
Classifier: Topic :: Internet :: WWW/HTTP :: WSGI :: Application
Classifier: Development Status :: 5 - Production/Stable
Classifier: Topic :: Internet :: WWW/HTTP :: Site Management :: Link Checking
Classifier: License :: OSI Approved :: GNU General Public License v2 (GPLv2)
